README.md
setup.py
dorian/__init__.py
dorian.egg-info/PKG-INFO
dorian.egg-info/SOURCES.txt
dorian.egg-info/dependency_links.txt
dorian.egg-info/not-zip-safe
dorian.egg-info/top_level.txt