Metadata-Version: 2.1
Name: dorian
Version: 0.0.1
Summary: A tool for Data-Oriented experiment Reproducibility, Inspection and AutomatioN
Home-page: http://github.com/sergred/dorian
Author: Sergey Redyuk
Author-email: sergred@gmail.com
License: Apache License 2.0
Platform: UNKNOWN
Classifier: Development Status :: 1 - Planning
Classifier: Programming Language :: Python :: 3.6
Classifier: License :: OSI Approved :: Apache Software License
Classifier: Operating System :: POSIX :: Linux
Classifier: Natural Language :: English
Classifier: Topic :: Scientific/Engineering
Classifier: Intended Audience :: Science/Research
